Assignment_7_190122_190997/Store_Load.v
// Amrit kumar --190122
// Yash Gupta ---190997


module Store_Load(
  input  reset,
  input [9:0] PC, 
  input [31:0] Data_Value,
  input [31:0] Address,
  input [31:0] Instruction,
  input Opcode_Data,
  output reg [31:0] Dataout
);

  wire [15:0] Offset;
  assign Offset= Instruction[15:0];

// wire [31:0] Data1, Data2;
// assign Data1= Register[Instruction[25:21]];
// assign Data2= Register[Instruction[20:16]];

  reg [31:0] Data_Memory [0:256];

	integer i;
	initial begin
		for (i=0; i < 256; i++) begin
      Data_Memory[i] = 0;
		end
    Data_Memory[0] = 32'd10;
    Data_Memory[1] = 32'd6;
    Data_Memory[2] = 32'd1;
    Data_Memory[3] = 32'd74;
    Data_Memory[4] = 32'd21;
    Data_Memory[5] = 32'd6;
    Data_Memory[6] = 32'd86;
    Data_Memory[7] = 32'd76;
    Data_Memory[8] = 32'd34;
    Data_Memory[9] = 32'd22;
    Data_Memory[10] = 32'd66;
	end


	always @(reset or Data_Value or Address or Offset or Opcode_Data) begin
    if (reset == 1) begin
      for (i = 0; i < 256; i = i + 1)
        Data_Memory[i] = 0;
    end
    else begin
      if (Opcode_Data) begin
        Data_Memory[Address[9:0] + Offset[9:0]] = Data_Value;
        $display("Data_Memory[%d] %d", Address[9:0] + Offset[9:0], Data_Memory[Address[9:0] + Offset[9:0]] );
      end
      else if (Opcode_Data == 1'b0) begin
        Dataout = Data_Memory[Address[9:0] + Offset[9:0]];
      end
	  end

    if(PC == 32'd24) begin
      for(i=1; i<=Data_Memory[0]; i++) begin
        $display("Data_Memory[%d] %d", i, Data_Memory[i]);
      end
    end

  end

endmodule

Assignment_7_190122_190997/Branch.v
// Amrit kumar --190122
// Yash Gupta ---190997


module Branching(
  input [31:0] Data1,
  input [31:0] Data2,
  input [31:0] Instruction,
  input [9:0] PC,   //program counter
  input [3:0] Opcode_Branch,
  output reg [9:0] Next_PC,
  output reg [9:0] ra
);

wire [25:0] Immediate_Jump;
assign Immediate_Jump= Instruction[25:0];


wire [15:0] Immediate_Branch;
assign Immediate_Branch= Instruction[15:0];

  initial begin
      ra=PC;          
  end

  always @(*) begin
    case (Opcode_Branch)

    4'b0000:Next_PC = ($signed(Data1) == $signed(Data2)) ? (PC + $signed(Immediate_Branch)) : PC ;   //beq
    4'b0001: Next_PC = ($signed(Data1) != $signed(Data2)) ? (PC + $signed(Immediate_Branch)) : PC;   //bne
    4'b0010:Next_PC = ($signed(Data1) > $signed(Data2)) ? (PC + $signed(Immediate_Branch)) :PC ;   //bgt
    4'b0011:Next_PC = ($signed(Data1) >= $signed(Data2)) ? (PC + $signed(Immediate_Branch)) : PC;    //bgte
    4'b0100:Next_PC = ($signed(Data1) < $signed(Data2)) ? (PC + $signed(Immediate_Branch)) : PC;   //ble
    4'b0101:Next_PC = ($signed(Data1) <= $signed(Data2)) ? (PC + $signed(Immediate_Branch)) : PC;    //bleq
    4'b0110: Next_PC= Immediate_Jump-1;      //j
    4'b0111: Next_PC= Data1-1;        //jr
    4'b1000:   begin
        ra=PC+1;                //jal
        Next_PC= $signed(Immediate_Jump)-1;
    end
    endcase

end


endmodule

Assignment_7_190122_190997/ALU.v
// Amrit kumar --190122
// Yash Gupta ---190997



module ALU(
  input [31:0] Data1,
  input [31:0] Data2,
  input [31:0] Instruction,
  input [3:0] Opcode_ALU,
  output reg [31:0] Result
);
  wire [15:0] Immediate_Branch;            // We will need this in case of I-type operations
  assign Immediate_Branch= Instruction[15:0];


  always @(*) begin
    case (Opcode_ALU)

    // for alu R-type(add, sub, addu, subu, and, or)
      4'b0000: Result = Data1 + Data2; //add
      4'b0001: Result = Data1 - Data2; //sub
      4'b0010: Result = Data1 + Data2; //addu d
      4'b0011: Result = Data1 - Data2; //subu d
    
      4'b0110: Result = Data1 & Data2; //and
      4'b0111: Result = Data1 | Data2; //or
      
      4'b0100: Result = Data1 + {{16{Immediate_Branch[15]}}, Immediate_Branch[15:0]}; //addi d
      4'b0101: Result = Data1 + {{16{1'b0}}, Immediate_Branch[15:0]}; //addiu  d

      
      4'b1000: Result = Data1 & {{16{Immediate_Branch[15]}}, Data2[15:0]}; //andi  d
      4'b1001: Result = Data1 | {{16{Immediate_Branch[15]}}, Data2[15:0]}; //ori  d

      // for comparision 
      4'b1010: Result = Data1 << Data2[4:0]; //sll
      4'b1011: Result = Data1 >> Data2[4:0]; //srl

      4'b1100: Result = ($signed(Data1) < $signed(Data2)) ? 1:0; //slt
      4'b1101:  Result = ($signed(Data1) < $signed({{16{1'b0}}, Immediate_Branch[15:0]}))?1:0 ; //slti

    endcase
  end

endmodule

Assignment_7_190122_190997/Decode.v

// Amrit kumar --190122
// Yash Gupta ---190997



// module Decode(
//   input [5:0] opcode,func,
//   output reg [3:0] Opcode_ALU, Opcode_Branch,   //stores opcode for alu and branch 
//   output reg Opcode_Data,       //stores opcode for data
//   output reg [2:0]Mode_    // will detect what type or mode instruction (R, I type)
  
// );



// //Mode_Type is 0 for Jr and 1 for all R-type ALU and 2 for all I-type ALU 



// //  wire [5:0] opcode; // stores from 31 to 26 bits from 32 bits instruction(provided above)
// //  wire [5:0] func;   // stores from lower 5 to 0 bits from 32 bits instruction(provided above)
 
//   // assign opcode = Instruction[31:26];
//   // assign func=Instruction[5:0];

// //   always @(opcode or func) begin
// //     Mode_Type=3'b000;
// //     Opcode_Data=0;
// //    if(opcode==6'b000000) begin
// //      Mode_Type=3'b001;   // i.e, its a R-type      1--for R-type 
// //     case(func)
// //     //for Arithmetic(add, sub, addu, subu-----using main mips func code)
// //     6'b100000:Opcode_ALU = 4'b0000;   //add32    0
// //     6'b100010:Opcode_ALU = 4'b0001;   //sub34    1 
// //     6'b100001:Opcode_ALU = 4'b0010;   //addu33   2
// //     6'b100011:Opcode_ALU = 4'b0011;  //subu35    3
// //     //Now for logical(and, or, sll, srl-----using main mips func code) 
// //     6'b100100:Opcode_ALU = 4'b0110;  //and36   6   
// //     6'b100101:Opcode_ALU = 4'b0111;  //or37    7
// //     6'b000000:Opcode_ALU = 4'b1010; //sll0     10 
// //     6'b000010:Opcode_ALU = 4'b1011; //srl2     11
// //     // now for comparison(slt------using main mips func code)
// //     6'b101010:Opcode_ALU = 4'b1100;   //slt42     12
// //     // 6'b001000: begin Opcode_Branch=4'b0111; Mode_Type=3'b000; end   //jr
   
// //     endcase
// //    end
// //     //Top 3 down else if cases are for the unconditional branches
// //     else if(opcode==6'b000010)begin
// //       Opcode_Branch=4'b0110;    // this is for j2    6
// //     end

// //     else if(opcode==6'b001000)begin
// //       Mode_Type=3'b000;       //this is for jr8(Jump back to caller) operation    7
// //       Opcode_Branch=4'b0111;
// //     end
  
// //     else if(opcode==6'b000011)begin
// //       Opcode_Branch=4'b1000;    //this is for jal3 operation    8
// //     end

// //   else begin
// //     case(opcode)
    
// //       //for data and alu(using main mips func code)
// //       6'b001100:
// //       begin Opcode_ALU = 4'b1000;             //andi12      8
// //             Mode_Type=3'b010;   
// //       end       
// //       6'b001001:
// //       begin
// //         Opcode_ALU = 4'b0101;         //addiu9      5
// //         Mode_Type=3'b010;
// //       end
// //       6'b001010:
// //       begin 
// //         Opcode_ALU = 4'b1101;         //slti10      13
// //         Mode_Type=3'b010;
// //       end
// //       6'b001000:
// //       begin 
// //         Opcode_ALU = 4'b0100;         // addi8      4
// //         Mode_Type=3'b010; 
// //       end
// //       6'b100011:
// //       begin 
// //         Opcode_Data=1'b0;              //lw35       0
// //         Mode_Type=3'b100;
// //       end
// //       6'b101011:
// //       begin 
// //         Opcode_Data=1'b1;            //sw43         1
// //         Mode_Type=3'b011; 
// //       end 
// //       6'b001101:
// //       begin 
// //         Opcode_ALU = 4'b1001;         //ori13       9
// //         Mode_Type=3'b010;
// //       end
// //       //for ONLY conditional branch(using main mips func code)
// //       6'b000100: Opcode_Branch = 4'b0000;  //beq4           0
// //       6'b000101: Opcode_Branch = 4'b0001;  //bne5           1
// //       6'b000111: Opcode_Branch = 4'b0010;  //bgt7           2
// //       6'b011000: Opcode_Branch = 4'b0011;  //bgte24         3
// //       6'b011001: Opcode_Branch = 4'b0100;  //ble25          4
// //       6'b010101: Opcode_Branch = 4'b0101;  //bleq21         5

// // endcase
// // end
// // end
// // $display(" %d", Opcode_ALU);




//  always @(opcode or func) begin
//     Mode = 3'b000;
//     Opcode_Data = 0;
//     if(opcode == 6'b000000) begin
//       Mode=2'b01;
//       case(func)
//         6'b100000: Opcode_ALU = 4'b0000; //add
//         6'b100010: Opcode_ALU = 4'b0001; //sub
//         6'b100001: Opcode_ALU = 4'b0010; //addu
//         6'b100011: Opcode_ALU = 4'b0011; //subu
//         6'b100100: Opcode_ALU = 4'b0110; //and
//         6'b100010: Opcode_ALU = 4'b0111; //or
//         6'b000000: Opcode_ALU = 4'b1010; //sll
//         6'b000010: Opcode_ALU = 4'b1011; //srl
//         6'b101010: Opcode_ALU = 4'b1100; //slt
//         6'b001000: begin Opcode_Branch = 4'b0111; Mode=3'b000; end//jr
//       endcase
//     end

//     else if(opcode == 6'b000010)
//       Opcode_Branch = 4'b0110; //j

//     else if(opcode == 6'b000011)
//       Opcode_Branch= 4'b1000; //jal

//     // I type instructions
//     else begin
//       case(opcode)
//         6'b001000: begin Opcode_ALU = 4'b0100; Mode = 3'b010; end //addi
//         6'b001001: begin Opcode_ALU = 4'b0101; Mode = 3'b010; end //addiu
//         6'b001100: begin Opcode_ALU = 4'b1000; Mode = 3'b010; end  //andi
//         6'b001101: begin Opcode_ALU = 4'b1001; Mode = 3'b010; end  //ori
//         6'b100011: begin Opcode_Data = 1'b0; Mode = 3'b100; end  //lw
//         6'b101011: begin Opcode_Data = 1'b1; Mode = 3'b011; end //sw
//         6'b000100: Opcode_Branch = 4'b0000;  //beq
//         6'b000101: Opcode_Branch = 4'b0001;  //bne
//         6'b000111: Opcode_Branch = 4'b0010;  //bgt
//         6'b011000: Opcode_Branch = 4'b0011;  //bgte/bge
//         6'b011001: Opcode_Branch = 4'b0100;  //ble/blt
//         6'b010101: Opcode_Branch = 4'b0101;  //bleq
//         6'b001010: begin Opcode_ALU = 4'b1101; Mode = 3'b010; end//slti
//       endcase
//     end
//   end
// endmodule

// module Decode(
//   input [31:0] Instruction,
//   output reg [3:0] Opcode_ALU, Opcode_Branch,
//   output reg Opcode_Data,
//   output reg[2:0] Mode
// );
// wire [5:0] opcode, func;
// assign opcode= Instruction[31:26];
// assign func= Instruction[5:0];

//   always @(opcode or func) begin
//     Mode = 3'b000;
//     Opcode_Data = 0;
//     if(opcode == 6'b000000) begin
//       Mode=3'b001;
//       case(func)
//         6'b100000: Opcode_ALU = 4'b0000; //add
//         6'b100010: Opcode_ALU = 4'b0001; //sub
//         6'b100001: Opcode_ALU = 4'b0010; //addu
//         6'b100011: Opcode_ALU = 4'b0011; //subu
//         6'b100100: Opcode_ALU = 4'b0110; //and
//         6'b100010: Opcode_ALU = 4'b0111; //or
//         6'b000000: Opcode_ALU = 4'b1010; //sll
//         6'b000010: Opcode_ALU = 4'b1011; //srl
//         6'b101010: Opcode_ALU = 4'b1100; //slt
//         6'b001000: begin Opcode_Branch = 4'b0111; Mode=3'b000; end//jr
//       endcase
//     end

//     else if(opcode == 6'b000010)
//       Opcode_Branch = 4'b0110; //j
      
//     else if(opcode==6'b001000)begin
//       Mode=3'b000;       //this is for jr8(Jump back to caller) operation    7
//       Opcode_Branch=4'b0111;
//     end

//     else if(opcode == 6'b000011)
//       Opcode_Branch= 4'b1000; //jal

//     // I type instructions
//     else begin
//       case(opcode)
//         6'b001000: begin Opcode_ALU = 4'b0100; Mode = 3'b010; end //addi
//         6'b001001: begin Opcode_ALU = 4'b0101; Mode = 3'b010; end //addiu
//         6'b001100: begin Opcode_ALU = 4'b1000; Mode = 3'b010; end  //andi
//         6'b001101: begin Opcode_ALU = 4'b1001; Mode = 3'b010; end  //ori
//         6'b100011: begin Opcode_Data = 1'b0; Mode = 3'b100; end  //lw
//         6'b101011: begin Opcode_Data = 1'b1; Mode = 3'b011; end //sw
//         6'b000100: Opcode_Branch = 4'b0000;  //beq
//         6'b000101: Opcode_Branch = 4'b0001;  //bne
//         6'b000111: Opcode_Branch = 4'b0010;  //bgt
//         6'b011000: Opcode_Branch = 4'b0011;  //bgte/bge
//         6'b011001: Opcode_Branch = 4'b0100;  //ble/blt
//         6'b010101: Opcode_Branch = 4'b0101;  //bleq
//         6'b001010: begin Opcode_ALU = 4'b1101; Mode = 3'b010; end//slti
//       endcase
//     end
//   end
  
// endmodule




module Decode(
  input [31:0] Instruction,
  output reg [3:0] Opcode_ALU, Opcode_Branch,
  output reg Opcode_Data,
  output reg[2:0] Mode
);
wire [5:0] opcode, func;
assign opcode= Instruction[31:26];
assign func= Instruction[5:0];
// here mode=0 for jr, 1 for R-type ALU, 2 for I-type, 3 for sw, 4 for lw
  always @(opcode or func) begin
    Mode = 3'b000; //this will be used for jr operation 
    Opcode_Data = 0;  //this is for lw
    if(opcode == 6'b000000) begin
      Mode=3'b001;
      case(func)

      // for Arithmetic(add, sub, addu, subu-----using main mips func code)
        6'b100000: begin 
          Opcode_ALU = 4'b0000;   //add32
        end
        6'b100010: begin            //sub34
          Opcode_ALU = 4'b0001; 
        end
        6'b100001: begin          //addu33
        Opcode_ALU = 4'b0010;
        end 
        6'b100011: begin          //subu35
          Opcode_ALU = 4'b0011; 
        end
        //Now for logical(and, or, sll, srl, slt-----using main mips func code)

        6'b100100: begin            //and36
          Opcode_ALU = 4'b0110;
        end 
        6'b100010: begin             //or37
          Opcode_ALU = 4'b0111;
        end 
        6'b000000: begin              //sll0 
          Opcode_ALU = 4'b1010; 
        end
        6'b000010: begin            //srl2
          Opcode_ALU = 4'b1011; 
        end
        6'b101010: begin              //slt42 
          Opcode_ALU = 4'b1100;
        end 
      endcase
    end
    //Top 3 down else if cases are for the unconditional branches

    else if(opcode == 6'b000010)begin
      Opcode_Branch = 4'b0110; //j2
    end

    else if(opcode==6'b000000 && func==001000)begin
      Mode=3'b000;       //this is for jr8(Jump back to caller) operation    7
      Opcode_Branch=4'b0111;
    end

    else if(opcode == 6'b000011)begin
      Opcode_Branch= 4'b1000; //jal3
    end

    // I type instructions

    else begin
      case(opcode)
        6'b001000: begin //addi8
          Opcode_ALU = 4'b0100;
          Mode = 3'b010; 
          end 
        6'b001001: begin //addiu9
          Opcode_ALU = 4'b0101; 
          Mode = 3'b010; 
          end 
        6'b001100: begin //andi12
          Opcode_ALU = 4'b1000; 
          Mode = 3'b010; 
          end  
        6'b001101: begin //ori13
          Opcode_ALU = 4'b1001; 
          Mode = 3'b010; 
          end  
        6'b101011: begin //sw43
          Opcode_Data = 1'b1; 
          Mode = 3'b011; 
          end 
        6'b100011: begin //lw35
          Opcode_Data = 1'b0; 
          Mode = 3'b100; 
          end
        6'b001010: begin  //slti
          Opcode_ALU = 4'b1101; 
          Mode = 3'b010; 
          end  
        6'b000100: Opcode_Branch = 4'b0000;  //beq4
        6'b000101: Opcode_Branch = 4'b0001;  //bne5
        6'b000111: Opcode_Branch = 4'b0010;  //bgt7
        6'b011000: Opcode_Branch = 4'b0011;  //bgte24
        6'b011001: Opcode_Branch = 4'b0100;  //blt25
        6'b010101: Opcode_Branch = 4'b0101;  //bleq21 
      endcase
    end
  end
  
endmodule

Assignment_7_190122_190997/Get_Instruction.v
// Amrit kumar --190122
// Yash Gupta ---190997

module Get_Instruction(
	input clk, reset,
	input [9:0] PC,
	output reg [31:0] Instruction
);

	reg [31:0] Instruction_Memory [0:512]; // 32-bit words of Instruction memory

	integer i;
	initial begin
		$readmemb("Instruction_File.bin", Instruction_Memory); //Loading contents from Intruction_file 
	end
// reading procedure for different address 
	always @(posedge clk) begin
		if (reset == 1) begin
      $readmemb("Instruction_File.bin", Instruction_Memory);
    end
		else begin
			Instruction = Instruction_Memory[PC]; // Select the instruction at the given address
			// $display("Values at DataMemory[%d]:---->%d", Instruction_Address, Data_Memory[Instruction_Address]);
	  end
	end
endmodule

Assignment_7_190122_190997/Fetch.v
// Amrit kumar --190122
// Yash Gupta ---190997


`include "Get_Instruction.v"
module Instruction_Fetch(
	input clk, reset,
	input [9:0] PC,
	output [31:0] Instruction
);

	Get_Instruction GI(.clk(clk), .reset(reset), .PC(PC), .Instruction(Instruction));

endmodule

Assignment_7_190122_190997/Main_Controller.v
// Amrit kumar --190122
// Yash Gupta ---190997


`include "Branch.v"
`include "ALU.v"
`include "Fetch.v"
`include "Decode.v"
`include "Store_Load.v"

module Main_Controller(
  input clk, reset
);
    reg [31:0] Register_Data [31:0]; // this my register memory to store the value of registers
  wire [31:0] Instruction; //32 bits instruction after performing fetching
  reg [9:0] PC;     //10 bits program counter (0 to 1023) 
  wire [9:0] Next_PC;       //will store our next instruction program counter 
  wire [9:0] ra;

    Instruction_Fetch I1(
    .clk(clk), 
    .reset(reset), 
    .PC(PC), 
    .Instruction(Instruction)
  );

  wire [3:0] Opcode_ALU;        // opcode for ALU operation
  wire [3:0] Opcode_Branch;     //opcode for Branching operations
  wire Opcode_Data;     //opcode for data (lw, sw)

  wire [31:0] Result, Dataout;
  wire [2:0] Mode_Type;


wire [5:0] Opcode;
wire [5:0] func;



assign Opcode= Instruction[31:25];
assign func= Instruction[5:0];

  Decode I2(
    .Instruction(Instruction), 
    .Opcode_ALU(Opcode_ALU), 
    .Opcode_Branch(Opcode_Branch), 
    .Opcode_Data(Opcode_Data),
    .Mode(Mode_Type)
  );
// always@(*)begin
//   $display("%d ---- %d ---- %d ----",Opcode_ALU, Opcode_Branch, Opcode_Data);
// end
wire [31:0] Data1, Data2;
assign Data1= Register_Data[Instruction[25:21]];
assign Data2= Register_Data[Instruction[20:16]];


//Now lets check what opcode value we get from fetch and according to that we will either ALU, branch, Stor_Load 
// if opcode 0--alu

// if(Opcode==32 || Opcode==34 || Opcode==33 || Opcode==35 || Opcode==36 || Opcode==37 || Opcode==0 || Opcode==2 || Opcode==42 || Opcode==8 || Opcode==9 || Opcode==12 || Opcode==13 ||Opcode==10)begin
//   ALU I3(
//     .Data1(Register[Instruction[25:21]]), 
//     .Data2(Register[Instruction[20:16]]), 
//     .Immediate_Branch(Instruction[15:0]),
//     .Opcode_ALU(Opcode_ALU), 
//     .Result(Result)
//   );
// end
// else if(Opcode==2 || Opcode==8 || Opcode==3 || Opcode==4 || Opcode==5 || Opcode==7 || Opcode==24 || Opcode==25 || Opcode==21)begin
//   Branching I4(
//     .Data1(Register[Instruction[25:21]]),
//     .Data2(Register[Instruction[20:16]]),
//     .Instruction(Instruction), 
//     .PC(PC), 
//     .Opcode_Branch(Opcode_Branch), 
//     .Next_PC(Next_PC), 
//     .ra(ra)
//   );
// end
// else if(Opcode==2 || Opcode==2)


  ALU I3(
    .Data1(Data1), 
    .Data2(Data2), 
    .Instruction(Instruction),
    .Opcode_ALU(Opcode_ALU), 
    .Result(Result)
  );

  Branching I4(
    .Data1(Data1),
    .Data2(Data2),
    .Instruction(Instruction), 
    .PC(PC), 
    .Opcode_Branch(Opcode_Branch), 
    .Next_PC(Next_PC), 
    .ra(ra)
  );
  wire [15:0] Offset;
  assign Offset= Instruction[15:0];

  Store_Load I5( 
    .reset(reset), 
    .PC(PC),
    .Data_Value(Data2), 
    .Address(Data1),
    .Instruction(Instruction),
    .Opcode_Data(Opcode_Data),
    .Dataout(Dataout)
  );

  initial begin
    Register_Data[0]=32'd0;
    PC=9'd0;
  end


  always @(negedge clk) begin
    if(Mode_Type==3'b000)begin
      PC = Next_PC + 1;                       // this is for Jr
    end

    else if(Mode_Type==3'b001)begin
      PC = PC + 1;
      Register_Data[Instruction[15:11]] = Result;    // this is for  R-type
    end

    else if(Mode_Type==3'b010)begin
      PC = PC + 1;                              // this is for I-type
      Register_Data[Instruction[20:16]] = Result;
    end

    else if(Mode_Type==3'b011)begin
      PC = PC + 1;                               // this is for sw (store)
    end

    else if(Mode_Type==3'b100)begin
      PC = PC + 1;
      Register_Data[Instruction[20:16]] = Dataout;         // this is for lw (load)
    end
    // $display("Below are values of register and PC");
    $display("Register_Data[%d] value is: %d -- Register_Data[%d] value is: %d -- Register_Data[%d] value is: %d -- Current_PC value is: %d", Instruction[25:21], Register_Data[Instruction[25:21]], Instruction[20:16], Register_Data[Instruction[20:16]], Instruction[15:11], Register_Data[Instruction[15:11]],PC);
    // $display("Datamemory %d",Data_Memory[3]);
  end
endmodule

Assignment_7_190122_190997/Main_Controller_test_bench.v

// Amrit kumar --190122
// Yash Gupta ---190997

`include "Main_Controller.v"
`timescale 1ps/1ps

module Main_Controller_test_bench;
    reg clk, reset;   
    Main_Controller M1(.clk(clk), .reset(reset));  ///calling main controller function for computation 

    initial begin                   //setting clock and reset values to zero
        clk=0;
        reset=0;
    end

    always #10 clk = ~clk;     // will invert clk value 
    initial begin
        $dumpfile("Main_Controller_test_bench.vcd");    
        $dumpvars(0, Main_Controller_test_bench);
        #15000 $finish;    //finish the whole program after 10000
    end


endmodule

Assignment_7_190122_190997/Main_Controller_test_bench.vcd
$date
	Sun Apr 16 16:22:06 2023
$end
$version
	Icarus Verilog
$end
$timescale
	1ps
$end
$scope module Main_Controller_test_bench $end
$var reg 1 ! clk $end
$var reg 1 " reset $end
$scope module M1 $end
$var wire 32 # Data1 [31:0] $end
$var wire 32 $ Data2 [31:0] $end
$var wire 1 ! clk $end
$var wire 1 " reset $end
$var wire 10 % ra [9:0] $end
$var wire 6 & func [5:0] $end
$var wire 32 ' Result [31:0] $end
$var wire 1 ( Opcode_Data $end
$var wire 4 ) Opcode_Branch [3:0] $end
$var wire 4 * Opcode_ALU [3:0] $end
$var wire 6 + Opcode [5:0] $end
$var wire 16 , Offset [15:0] $end
$var wire 10 - Next_PC [9:0] $end
$var wire 3 . Mode_Type [2:0] $end
$var wire 32 / Instruction [31:0] $end
$var wire 32 0 Dataout [31:0] $end
$var reg 10 1 PC [9:0] $end
$scope module I1 $end
$var wire 10 2 PC [9:0] $end
$var wire 1 ! clk $end
$var wire 1 " reset $end
$var wire 32 3 Instruction [31:0] $end
$scope module GI $end
$var wire 10 4 PC [9:0] $end
$var wire 1 ! clk $end
$var wire 1 " reset $end
$var reg 32 5 Instruction [31:0] $end
$upscope $end
$upscope $end
$scope module I2 $end
$var wire 32 6 Instruction [31:0] $end
$var wire 6 7 opcode [5:0] $end
$var wire 6 8 func [5:0] $end
$var reg 3 9 Mode [2:0] $end
$var reg 4 : Opcode_ALU [3:0] $end
$var reg 4 ; Opcode_Branch [3:0] $end
$var reg 1 ( Opcode_Data $end
$upscope $end
$scope module I3 $end
$var wire 32 < Data1 [31:0] $end
$var wire 32 = Data2 [31:0] $end
$var wire 32 > Instruction [31:0] $end
$var wire 4 ? Opcode_ALU [3:0] $end
$var wire 16 @ Immediate_Branch [15:0] $end
$var reg 32 A Result [31:0] $end
$upscope $end
$scope module I4 $end
$var wire 32 B Data1 [31:0] $end
$var wire 32 C Data2 [31:0] $end
$var wire 32 D Instruction [31:0] $end
$var wire 4 E Opcode_Branch [3:0] $end
$var wire 10 F PC [9:0] $end
$var wire 26 G Immediate_Jump [25:0] $end
$var wire 16 H Immediate_Branch [15:0] $end
$var reg 10 I Next_PC [9:0] $end
$var reg 10 J ra [9:0] $end
$upscope $end
$scope module I5 $end
$var wire 32 K Address [31:0] $end
$var wire 32 L Data_Value [31:0] $end
$var wire 32 M Instruction [31:0] $end
$var wire 1 ( Opcode_Data $end
$var wire 10 N PC [9:0] $end
$var wire 1 " reset $end
$var wire 16 O Offset [15:0] $end
$var reg 32 P Dataout [31:0] $end
$var integer 32 Q i [31:0] $end
$upscope $end
$upscope $end
$upscope $end
$enddefinitions $end
$comment Show the parameter values. $end
$dumpall
$end
#0
$dumpvars
b100000000 Q
bx P
bx O
b0 N
bx M
bx L
bx K
bx J
bx I
bx H
bx G
b0 F
bx E
bx D
bx C
bx B
bx A
bx @
bx ?
bx >
bx =
bx <
bx ;
bx :
bx 9
bx 8
bx 7
bx 6
bx 5
b0 4
bx 3
b0 2
b0 1
bx 0
bx /
bx .
bx -
bx ,
bx +
bx *
bx )
x(
bx '
bx &
bx %
bx $
bx #
0"
0!
$end
#10
b1010 0
b1010 P
0(
b100 .
b100 9
b110 +
b100011 7
b0 8
b0 @
b10000000000000000000 G
b0 H
b0 O
b0 ,
b0 #
b0 <
b0 B
b0 K
b0 &
b10001100000010000000000000000000 /
b10001100000010000000000000000000 3
b10001100000010000000000000000000 5
b10001100000010000000000000000000 6
b10001100000010000000000000000000 >
b10001100000010000000000000000000 D
b10001100000010000000000000000000 M
1!
#20
b1010 $
b1010 =
b1010 C
b1010 L
b1 1
b1 2
b1 4
b1 F
b1 N
0!
#30
b10010000000000000000 G
bx $
bx =
bx C
bx L
b10001100000010010000000000000000 /
b10001100000010010000000000000000 3
b10001100000010010000000000000000 5
b10001100000010010000000000000000 6
b10001100000010010000000000000000 >
b10001100000010010000000000000000 D
b10001100000010010000000000000000 M
1!
#40
b1010 $
b1010 =
b1010 C
b1010 L
b10 1
b10 2
b10 4
b10 F
b10 N
0!
#50
b1 '
b1 A
b100 *
b100 :
b100 ?
b10 .
b10 9
b110 0
b110 P
b10000 +
b1000 7
b1 8
b1 @
b1010000000000000001 G
b1 H
b1 O
b1 ,
bx $
bx =
bx C
bx L
b1 &
b100000000001010000000000000001 /
b100000000001010000000000000001 3
b100000000001010000000000000001 5
b100000000001010000000000000001 6
b100000000001010000000000000001 >
b100000000001010000000000000001 D
b100000000001010000000000000001 M
1!
#60
b1 $
b1 =
b1 C
b1 L
b11 1
b11 2
b11 4
b11 F
b11 N
0!
#70
b10 .
b10 9
b1001 '
b1001 A
b10110 0
b10110 P
b111111 8
b1111111111111111 @
b1001010011111111111111111 G
b1111111111111111 H
b1111111111111111 O
b1111111111111111 ,
b1010 $
b1010 =
b1010 C
b1010 L
b1010 #
b1010 <
b1010 B
b1010 K
b111111 &
b100001001010011111111111111111 /
b100001001010011111111111111111 3
b100001001010011111111111111111 5
b100001001010011111111111111111 6
b100001001010011111111111111111 >
b100001001010011111111111111111 D
b100001001010011111111111111111 M
1!
#80
b1000 '
b1000 A
b100010 0
b100010 P
b1001 #
b1001 <
b1001 B
b1001 K
b1001 $
b1001 =
b1001 C
b1001 L
b100 1
b100 2
b100 4
b100 F
b100 N
0!
#90
b100 -
b100 I
b100 )
b100 ;
b100 E
b0 .
b0 9
b11100 '
b11100 A
b0 0
b0 P
b110010 +
b11001 7
b10011 8
b10011 @
b1001000000000000000010011 G
b10011 H
b10011 O
b10011 ,
b0 $
b0 =
b0 C
b0 L
b10011 &
b1100101001000000000000000010011 /
b1100101001000000000000000010011 3
b1100101001000000000000000010011 5
b1100101001000000000000000010011 6
b1100101001000000000000000010011 >
b1100101001000000000000000010011 D
b1100101001000000000000000010011 M
1!
#100
b101 -
b101 I
b101 1
b101 2
b101 4
b101 F
b101 N
0!
#110
b0 *
b0 :
b0 ?
b1 .
b1 9
b0 '
b0 A
b0 +
b0 7
b100000 8
b101000000100000 @
b101000000100000 G
b101000000100000 H
b101000000100000 O
b101000000100000 ,
b0 #
b0 <
b0 B
b0 K
b100000 &
b101000000100000 /
b101000000100000 3
b101000000100000 5
b101000000100000 6
b101000000100000 >
b101000000100000 D
b101000000100000 M
1!
#120
b110 -
b110 I
b110 1
b110 2
b110 4
b110 F
b110 N
0!
#130
b11 )
b11 ;
b11 E
b0 .
b0 9
b1001 '
b1001 A
b110 -
b110 I
bx 0
bx P
b110000 +
b11000 7
b111100 8
b1111111111111100 @
b1010010011111111111111100 G
b1111111111111100 H
b1111111111111100 O
b1111111111111100 ,
b1001 $
b1001 =
b1001 C
b1001 L
b111100 &
b1100001010010011111111111111100 /
b1100001010010011111111111111100 3
b1100001010010011111111111111100 5
b1100001010010011111111111111100 6
b1100001010010011111111111111100 >
b1100001010010011111111111111100 D
b1100001010010011111111111111100 M
1!
#140
b111 -
b111 I
b111 1
b111 2
b111 4
b111 F
b111 N
0!
#150
b1 .
b1 9
b1 '
b1 A
b100111 -
b100111 I
b0 0
b0 P
b0 +
b0 7
b100000 8
b111000000100000 @
b101010100111000000100000 G
b111000000100000 H
b111000000100000 O
b111000000100000 ,
b0 $
b0 =
b0 C
b0 L
b1 #
b1 <
b1 B
b1 K
b100000 &
b101010100111000000100000 /
b101010100111000000100000 3
b101010100111000000100000 5
b101010100111000000100000 6
b101010100111000000100000 >
b101010100111000000100000 D
b101010100111000000100000 M
1!
#160
b101000 -
b101000 I
b1000 1
b1000 2
b1000 4
b1000 F
b1000 N
0!
#170
b100 .
b100 9
bx '
bx A
b1000 -
b1000 I
b110 0
b110 P
b110 +
b100011 7
b0 8
b0 @
b1110010110000000000000000 G
b0 H
b0 O
b0 ,
bx $
bx =
bx C
bx L
b0 &
b10001101110010110000000000000000 /
b10001101110010110000000000000000 3
b10001101110010110000000000000000 5
b10001101110010110000000000000000 6
b10001101110010110000000000000000 >
b10001101110010110000000000000000 D
b10001101110010110000000000000000 M
1!
#180
b111 '
b111 A
b1001 -
b1001 I
b110 $
b110 =
b110 C
b110 L
b1001 1
b1001 2
b1001 4
b1001 F
b1001 N
0!
#190
b100 *
b100 :
b100 ?
b10 .
b10 9
b1 '
b1 A
b10xx -
b10xx I
b10000 +
b1000 7
b1 8
b1 @
b1010011000000000000000001 G
b1 H
b1 O
b1 ,
bx $
bx =
bx C
bx L
b0 #
b0 <
b0 B
b0 K
b1 &
b100001010011000000000000000001 /
b100001010011000000000000000001 3
b100001010011000000000000000001 5
b100001010011000000000000000001 6
b100001010011000000000000000001 >
b100001010011000000000000000001 D
b100001010011000000000000000001 M
1!
#200
b1010 -
b1010 I
b1 $
b1 =
b1 C
b1 L
b1010 1
b1010 2
b1010 4
b1010 F
b1010 N
0!
