Assignment-3/Moore_type_model.v
module Moore_type_model(clock,reset,i_p,o_p);
input   clock,reset;
input  i_p;
output reg o_p;
reg[1:0]state;
reg[1:0]next_state;
always @ (clock)
begin
  if(reset)
  begin
  state=2'b00;
  end
  else
  begin
case(state)
   2'b00 : if (i_p == 1'b1) begin
                state <= 2'b01;
                o_p<=0;
              end
              else begin
                state <= 2'b00;
                o_p<=0;
              end
   2'b01 : if (i_p == 1'b1) begin
                state <= 2'b01;
                o_p<=0;
          end
          else begin
            state <= 2'b10;
            o_p<=0;
            //$display(i_p);
          end
   2'b10 : if (i_p == 1'b1) begin
                state <= 2'b11;
                o_p<=0;
              end
              else begin
                state <= 2'b00;
                o_p<=0;
              end
    2'b11 : if (i_p == 1'b1) begin
                state <= 2'b01;
                o_p<=0;
              end
              else begin
                state <= 2'b10;
                o_p<=1;
              end
   default : state <= 2'b00;
  endcase
  end
end

endmodule

Assignment-3/Moore_type_model_tb.v
`include "Moore_type_model.v"
module Moore_type_model_tb;
reg clock,i_p,reset;
wire o_p;
Moore_type_model uut (.clock(clock),.reset(reset),.i_p(i_p),.o_p(o_p));
initial begin
   $dumpfile("Moore_type_model.vcd");
    $dumpvars(0,Moore_type_model_tb);
    reset=1'b1;
    clock=0;
    #20
    reset=1'b0;
    i_p=0;
    clock=1;
    #20
    $display(o_p);
    i_p=1;
    clock=0;
    #20
    $display(o_p);
    i_p=1;
    clock=1;
    #20
    $display(o_p);
    i_p=0;
    clock=0;
    #20
    $display(o_p);
    i_p=0;
    clock=1;
    #20
    $display(o_p);
    i_p=1;
    clock=0;
    #20
    $display(o_p);
    i_p=0;
    clock =1;
    #20
    $display(o_p);
    i_p=1;
    clock=0;
    #20
    $display(o_p);
    i_p=0;
    clock=1;
    #20
    $display(o_p);
    #69
    $finish;
end
endmodule

Assignment-3/Moore_type_model.vcd
$date
	Tue Feb 07 14:40:24 2023
$end
$version
	Icarus Verilog
$end
$timescale
	1s
$end
$scope module Moore_type_model_tb $end
$var wire 1 ! o_p $end
$var reg 1 " clock $end
$var reg 1 # i_p $end
$var reg 1 $ reset $end
$scope module uut $end
$var wire 1 " clock $end
$var wire 1 # i_p $end
$var wire 1 $ reset $end
$var reg 1 ! o_p $end
$var reg 2 % state [1:0] $end
$upscope $end
$upscope $end
$enddefinitions $end
$comment Show the parameter values. $end
$dumpall
$end
#0
$dumpvars
b0 %
1$
x#
0"
x!
$end
#20
0!
1"
0#
0$
#40
b1 %
0"
1#
#60
1"
#80
b10 %
0"
0#
#100
b0 %
1"
#120
b1 %
0"
1#
#140
b10 %
1"
0#
#160
b11 %
0"
1#
#180
1!
b10 %
1"
0#
