Assignment-1/decoder_3_8.v
`timescale 1ns / 1ps 
module decoder_3_8 (in, out, en);
input [2:0] in;
input en;
output [7:0] out;
  reg [7:0] out;

 always @( in or en)
	begin
      if (en) 
        begin
          out=8'b00000000;
          case (in)
              3'b000: out=8'b00000001;
              3'b001: out=8'b00000010;
              3'b010: out=8'b00000100;
              3'b011: out=8'b00001000;
              3'b100: out=8'b00010000;
              3'b101: out=8'b00100000;
              3'b110: out=8'b01000000;
              3'b111: out=8'b10000000;
              default: out=8'b00000000;
          endcase
      end
else 
out=8'b00000000;
end
endmodule

Assignment-1/decoder_3_8_tb.v
`timescale 1ns / 1ps
`include "decoder_3_8.v"
module decoder_3_8_tb;
reg [2:0] in;
wire [7:0] out;
reg en;
decoder_3_8 uut(
    .in(in),
    .out(out),
    .en(en)
);
initial begin
    $dumpfile("decoder_3_8_tb.vcd");
    $dumpvars(0, decoder_3_8_tb);
    en=1'b1;
    in = 3'b000;
    #1;
    in = 3'b001;
    #1;
    in = 3'b010;
    #1;
    in = 3'b011;
    #1;
    in = 3'b100;
    #1;
    in = 3'b101;
    #1;
    in = 3'b110;
    #1;
    in = 3'b111;
    #1;


    en= 1'b0;
    in = 3'b111;
    #1;


end
endmodule

Assignment-1/decoder_3_8_tb.vcd
$date
	Tue Jan 24 14:35:02 2023
$end
$version
	Icarus Verilog
$end
$timescale
	1ps
$end
$scope module decoder_3_8_tb $end
$var wire 8 ! out [7:0] $end
$var reg 1 " en $end
$var reg 3 # in [2:0] $end
$scope module uut $end
$var wire 1 " en $end
$var wire 3 $ in [2:0] $end
$var reg 8 % out [7:0] $end
$upscope $end
$upscope $end
$enddefinitions $end
$comment Show the parameter values. $end
$dumpall
$end
#0
$dumpvars
b1 %
b0 $
b0 #
1"
b1 !
$end
#1000
b10 !
b10 %
b1 #
b1 $
#2000
b100 !
b100 %
b10 #
b10 $
#3000
b1000 !
b1000 %
b11 #
b11 $
#4000
b10000 !
b10000 %
b100 #
b100 $
#5000
b100000 !
b100000 %
b101 #
b101 $
#6000
b1000000 !
b1000000 %
b110 #
b110 $
#7000
b10000000 !
b10000000 %
b111 #
b111 $
#8000
b0 !
b0 %
0"
