Assignment_7_Final/Store_Load.v
module Store_Load(
  input  reset,
  input [9:0] PC, 
  input [31:0] Data_Value,
  input [31:0] Address,
  input [15:0] Offset,
  input Opcode_Data,
  output reg [31:0] Dataout
);

  // wire [15:0] Offset;
  // assign Offset= Instruction[15:0];

// wire [31:0] Data1, Data2;
// assign Data1= Register[Instruction[25:21]];
// assign Data2= Register[Instruction[20:16]];

  reg [31:0] Data_Memory [0:1023];

	integer i;
	initial begin
		for (i=0; i < 1024; i++) begin
      Data_Memory[i] = 0;
		end
    Data_Memory[0] = 32'd10;
    Data_Memory[1] = 32'd5;
    Data_Memory[2] = 32'd2;
    Data_Memory[3] = 32'd7;
    Data_Memory[4] = 32'd11;
    Data_Memory[5] = 32'd9;
    Data_Memory[6] = 32'd4;
    Data_Memory[7] = 32'd15;
    Data_Memory[8] = 32'd0;
    Data_Memory[9] = 32'd12;
    Data_Memory[10] = 32'd3;
	end


	always @(reset or Data_Value or Address or Offset or Opcode_Data) begin
    if (reset == 1) begin
      for (i = 0; i < 1024; i = i + 1)
        Data_Memory[i] = 0;
    end
    else begin
      if (Opcode_Data) begin
        Data_Memory[Address[9:0] + Offset[9:0]] = Data_Value;
        $display("Data_Memory[%d] %d", Address[9:0] + Offset[9:0], Data_Memory[Address[9:0] + Offset[9:0]] );
      end
      else if (Opcode_Data == 1'b0) begin
        Dataout = Data_Memory[Address[9:0] + Offset[9:0]];
      end
	  end

    if(PC == 32'd24) begin
      for(i=1; i<=Data_Memory[0]; i++) begin
        $display("Data_Memory[%d] %d", i, Data_Memory[i]);
      end
    end
  end

endmodule

Assignment_7_Final/branch_operation.v
module Branching(
  input [31:0] Data1,
  input [31:0] Data2,
  input [25:0] Immediate_Jump,
  input [9:0] PC,   //program counter
  input [3:0] Opcode_Branch,
  output reg [9:0] Next_PC,
  output reg [9:0] ra
);

//rs,rt, immediate has the immediate /address why is immediate 32 bit value?

// wire [25:0] Immediate_Jump;
// assign Immediate= Instruction[25:0];


// wire [25:0] Immediate_Branch;
// assign Immediate= Instruction[15:0];

  initial begin
      ra=PC;          //store the current PC value to get back here if we encounter jr operation 
  end

  always @(*) begin
    case (Opcode_Branch)

    4'b0000:Next_PC = ($signed(Data1) == $signed(Data2)) ? (PC + $signed(Immediate_Jump[15:0])) : PC ;   //beq

    4'b0001: Next_PC = ($signed(Data1) != $signed(Data2)) ? (PC + $signed(Immediate_Jump[15:0])) : PC;   //bne

    4'b0010:Next_PC = ($signed(Data1) > $signed(Data2)) ? (PC + $signed(Immediate_Jump[15:0])) :PC ;   //bgt

    4'b0011:Next_PC = ($signed(Data1) >= $signed(Data2)) ? (PC + $signed(Immediate_Jump[15:0])) : PC;    //bgte

    4'b0100:Next_PC = ($signed(Data1) < $signed(Data2)) ? (PC + $signed(Immediate_Jump[15:0])) : PC;   //ble

    4'b0101:Next_PC = ($signed(Data1) <= $signed(Data2)) ? (PC + $signed(Immediate_Jump[15:0])) : PC;    //bleq

    4'b0110: Next_PC= Immediate_Jump-1;      //j

    4'b0111: Next_PC= Data1-1;        //jr

    4'b1000:   begin
        ra=PC+1;                //jal
        Next_PC= $signed(Immediate_Jump)-1;
    end
    endcase

end


endmodule

Assignment_7_Final/ALU.v
module ALU(
  input [31:0] Data1,
  input [31:0] Data2,
  input [15:0] Immediate_Branch,
  input [3:0] Opcode_ALU,
  output reg [31:0] Result
);
  // wire [15:0] Immediate;            // We will need this in case of I-type operations
  // assign Immediate= Instruction[15:0];


  always @(*) begin
    case (Opcode_ALU)

    // for alu R-type(add, sub, addu, subu, and, or)
      4'b0000: Result = Data1 + Data2; //add
      4'b0001: Result = Data1 - Data2; //sub
      4'b0010: Result = Data1 + Data2; //addu d
      4'b0011: Result = Data1 - Data2; //subu d
    
      4'b0110: Result = Data1 & Data2; //and
      4'b0111: Result = Data1 | Data2; //or
      //4'b0100: result = operand1 + {{16{operand1[15]}}, operand2[15:0]}; //addi d
      4'b0100: Result = Data1 + {{16{Immediate_Branch[15]}}, Immediate_Branch[15:0]}; //addi d
      4'b0101: Result = Data1 + {{16{1'b0}}, Immediate_Branch[15:0]}; //addiu  d

      
      4'b1000: Result = Data1 & {{16{Immediate_Branch[15]}}, Data2[15:0]}; //andi  d
      4'b1001: Result = Data1 | {{16{Immediate_Branch[15]}}, Data2[15:0]}; //ori  d

      // for comparision 
      4'b1010: Result = Data1 << Data2[4:0]; //sll
      4'b1011: Result = Data1 >> Data2[4:0]; //srl

      // 4'b1100: Result = Data1 << Data2[4:0]; //slt
      // 4'b1101: Result = Data1 >> Data2[4:0]; //srl
      4'b1100: Result = ($signed(Data1) < $signed(Data2)) ? 1:0; //slt
      4'b1101:  Result = ($signed(Data1) < $signed({{16{1'b0}}, Immediate_Branch[15:0]}))?1:0 ; //slti

    endcase
  end

endmodule

Assignment_7_Final/Decode.v
// module Decode(
//   input [5:0] opcode,func,
//   output reg [3:0] Opcode_ALU, Opcode_Branch,   //stores opcode for alu and branch 
//   output reg Opcode_Data,       //stores opcode for data
//   output reg [2:0]Mode_    // will detect what type or mode instruction (R, I type)
  
// );



// //Mode_Type is 0 for Jr and 1 for all R-type ALU and 2 for all I-type ALU 



// //  wire [5:0] opcode; // stores from 31 to 26 bits from 32 bits instruction(provided above)
// //  wire [5:0] func;   // stores from lower 5 to 0 bits from 32 bits instruction(provided above)
 
//   // assign opcode = Instruction[31:26];
//   // assign func=Instruction[5:0];

// //   always @(opcode or func) begin
// //     Mode_Type=3'b000;
// //     Opcode_Data=0;
// //    if(opcode==6'b000000) begin
// //      Mode_Type=3'b001;   // i.e, its a R-type      1--for R-type 
// //     case(func)
// //     //for Arithmetic(add, sub, addu, subu-----using main mips func code)
// //     6'b100000:Opcode_ALU = 4'b0000;   //add32    0
// //     6'b100010:Opcode_ALU = 4'b0001;   //sub34    1 
// //     6'b100001:Opcode_ALU = 4'b0010;   //addu33   2
// //     6'b100011:Opcode_ALU = 4'b0011;  //subu35    3
// //     //Now for logical(and, or, sll, srl-----using main mips func code) 
// //     6'b100100:Opcode_ALU = 4'b0110;  //and36   6   
// //     6'b100101:Opcode_ALU = 4'b0111;  //or37    7
// //     6'b000000:Opcode_ALU = 4'b1010; //sll0     10 
// //     6'b000010:Opcode_ALU = 4'b1011; //srl2     11
// //     // now for comparison(slt------using main mips func code)
// //     6'b101010:Opcode_ALU = 4'b1100;   //slt42     12
// //     // 6'b001000: begin Opcode_Branch=4'b0111; Mode_Type=3'b000; end   //jr
   
// //     endcase
// //    end
// //     //Top 3 down else if cases are for the unconditional branches
// //     else if(opcode==6'b000010)begin
// //       Opcode_Branch=4'b0110;    // this is for j2    6
// //     end

// //     else if(opcode==6'b001000)begin
// //       Mode_Type=3'b000;       //this is for jr8(Jump back to caller) operation    7
// //       Opcode_Branch=4'b0111;
// //     end
  
// //     else if(opcode==6'b000011)begin
// //       Opcode_Branch=4'b1000;    //this is for jal3 operation    8
// //     end

// //   else begin
// //     case(opcode)
    
// //       //for data and alu(using main mips func code)
// //       6'b001100:
// //       begin Opcode_ALU = 4'b1000;             //andi12      8
// //             Mode_Type=3'b010;   
// //       end       
// //       6'b001001:
// //       begin
// //         Opcode_ALU = 4'b0101;         //addiu9      5
// //         Mode_Type=3'b010;
// //       end
// //       6'b001010:
// //       begin 
// //         Opcode_ALU = 4'b1101;         //slti10      13
// //         Mode_Type=3'b010;
// //       end
// //       6'b001000:
// //       begin 
// //         Opcode_ALU = 4'b0100;         // addi8      4
// //         Mode_Type=3'b010; 
// //       end
// //       6'b100011:
// //       begin 
// //         Opcode_Data=1'b0;              //lw35       0
// //         Mode_Type=3'b100;
// //       end
// //       6'b101011:
// //       begin 
// //         Opcode_Data=1'b1;            //sw43         1
// //         Mode_Type=3'b011; 
// //       end 
// //       6'b001101:
// //       begin 
// //         Opcode_ALU = 4'b1001;         //ori13       9
// //         Mode_Type=3'b010;
// //       end
// //       //for ONLY conditional branch(using main mips func code)
// //       6'b000100: Opcode_Branch = 4'b0000;  //beq4           0
// //       6'b000101: Opcode_Branch = 4'b0001;  //bne5           1
// //       6'b000111: Opcode_Branch = 4'b0010;  //bgt7           2
// //       6'b011000: Opcode_Branch = 4'b0011;  //bgte24         3
// //       6'b011001: Opcode_Branch = 4'b0100;  //ble25          4
// //       6'b010101: Opcode_Branch = 4'b0101;  //bleq21         5

// // endcase
// // end
// // end
// // $display(" %d", Opcode_ALU);




//  always @(opcode or func) begin
//     Mode = 3'b000;
//     Opcode_Data = 0;
//     if(opcode == 6'b000000) begin
//       Mode=2'b01;
//       case(func)
//         6'b100000: Opcode_ALU = 4'b0000; //add
//         6'b100010: Opcode_ALU = 4'b0001; //sub
//         6'b100001: Opcode_ALU = 4'b0010; //addu
//         6'b100011: Opcode_ALU = 4'b0011; //subu
//         6'b100100: Opcode_ALU = 4'b0110; //and
//         6'b100010: Opcode_ALU = 4'b0111; //or
//         6'b000000: Opcode_ALU = 4'b1010; //sll
//         6'b000010: Opcode_ALU = 4'b1011; //srl
//         6'b101010: Opcode_ALU = 4'b1100; //slt
//         6'b001000: begin Opcode_Branch = 4'b0111; Mode=3'b000; end//jr
//       endcase
//     end

//     else if(opcode == 6'b000010)
//       Opcode_Branch = 4'b0110; //j

//     else if(opcode == 6'b000011)
//       Opcode_Branch= 4'b1000; //jal

//     // I type instructions
//     else begin
//       case(opcode)
//         6'b001000: begin Opcode_ALU = 4'b0100; Mode = 3'b010; end //addi
//         6'b001001: begin Opcode_ALU = 4'b0101; Mode = 3'b010; end //addiu
//         6'b001100: begin Opcode_ALU = 4'b1000; Mode = 3'b010; end  //andi
//         6'b001101: begin Opcode_ALU = 4'b1001; Mode = 3'b010; end  //ori
//         6'b100011: begin Opcode_Data = 1'b0; Mode = 3'b100; end  //lw
//         6'b101011: begin Opcode_Data = 1'b1; Mode = 3'b011; end //sw
//         6'b000100: Opcode_Branch = 4'b0000;  //beq
//         6'b000101: Opcode_Branch = 4'b0001;  //bne
//         6'b000111: Opcode_Branch = 4'b0010;  //bgt
//         6'b011000: Opcode_Branch = 4'b0011;  //bgte/bge
//         6'b011001: Opcode_Branch = 4'b0100;  //ble/blt
//         6'b010101: Opcode_Branch = 4'b0101;  //bleq
//         6'b001010: begin Opcode_ALU = 4'b1101; Mode = 3'b010; end//slti
//       endcase
//     end
//   end
// endmodule

module Decode(
  input [31:0] Instruction,
  output reg [3:0] Opcode_ALU, Opcode_Branch,
  output reg Opcode_Data,
  output reg[2:0] Mode
);
wire [5:0] opcode, func;
assign opcode= Instruction[31:26];
assign func= Instruction[5:0];

  always @(opcode or func) begin
    Mode = 3'b000;
    Opcode_Data = 0;
    if(opcode == 6'b000000) begin
      Mode=2'b01;
      case(func)
        6'b100000: Opcode_ALU = 4'b0000; //add
        6'b100010: Opcode_ALU = 4'b0001; //sub
        6'b100001: Opcode_ALU = 4'b0010; //addu
        6'b100011: Opcode_ALU = 4'b0011; //subu
        6'b100100: Opcode_ALU = 4'b0110; //and
        6'b100010: Opcode_ALU = 4'b0111; //or
        6'b000000: Opcode_ALU = 4'b1010; //sll
        6'b000010: Opcode_ALU = 4'b1011; //srl
        6'b101010: Opcode_ALU = 4'b1100; //slt
        6'b001000: begin Opcode_Branch = 4'b0111; Mode=3'b000; end//jr
      endcase
    end

    else if(opcode == 6'b000010)
      Opcode_Branch = 4'b0110; //j

    else if(opcode == 6'b000011)
      Opcode_Branch= 4'b1000; //jal

    // I type instructions
    else begin
      case(opcode)
        6'b001000: begin Opcode_ALU = 4'b0100; Mode = 3'b010; end //addi
        6'b001001: begin Opcode_ALU = 4'b0101; Mode = 3'b010; end //addiu
        6'b001100: begin Opcode_ALU = 4'b1000; Mode = 3'b010; end  //andi
        6'b001101: begin Opcode_ALU = 4'b1001; Mode = 3'b010; end  //ori
        6'b100011: begin Opcode_Data = 1'b0; Mode = 3'b100; end  //lw
        6'b101011: begin Opcode_Data = 1'b1; Mode = 3'b011; end //sw
        6'b000100: Opcode_Branch = 4'b0000;  //beq
        6'b000101: Opcode_Branch = 4'b0001;  //bne
        6'b000111: Opcode_Branch = 4'b0010;  //bgt
        6'b011000: Opcode_Branch = 4'b0011;  //bgte/bge
        6'b011001: Opcode_Branch = 4'b0100;  //ble/blt
        6'b010101: Opcode_Branch = 4'b0101;  //bleq
        6'b001010: begin Opcode_ALU = 4'b1101; Mode = 3'b010; end//slti
      endcase
    end
  end
  
endmodule

Assignment_7_Final/instruction_fetch.v
module instruction_memory(
	input clk, reset,
	input [9:0] Instruction_Address,
	output reg [31:0] Instruction
);

	reg [31:0] Data_Memory [0:1023]; // 1024 32-bit words of memory

	integer i;
	initial begin
		$readmemb("instructions.bin", Data_Memory); // Read the instructions from a hex file
		
		for(i=0; i<30; i = i+1) begin
			$display("memory[%d] = %b", i, Data_Memory[i]);
		end
	end

	always @(posedge clk) begin
		if (reset == 1) begin
      $readmemb("instructions.bin", Data_Memory);
    end
		else begin
			Instruction = Data_Memory[Instruction_Address]; // Select the instruction at the given address
			// $display("Values at DataMemory[%d]:---->%d", Instruction_Address, Data_Memory[Instruction_Address]);
	  end
	end
endmodule

module Instruction_Fetch(
	input clk, reset,
	input [9:0] PC,
	output [31:0] Instruction
);

	instruction_memory IM(.clk(clk), .reset(reset), .Instruction_Address(PC), .Instruction(Instruction));

endmodule

Assignment_7_Final/Main_Controller.v
`include "branch_operation.v"
`include "ALU.v"
`include "instruction_fetch.v"
`include "Decode.v"
`include "Store_Load.v"

module Main_Controller(
  input clk, reset
);
    reg [31:0] Register [31:0]; // this my register memory to store the value of registers
  wire [31:0] Instruction; //32 bits instruction after performing fetching
  reg [9:0] PC;     //10 bits program counter (0 to 1023) 
  wire [9:0] Next_PC, ra;       //will store our next instruction program counter 
  



  wire [3:0] Opcode_ALU;        // opcode for ALU operation
  wire [3:0] Opcode_Branch;     //opcode for Branching operations
  wire Opcode_Data;     //opcode for data (lw, sw)

  wire [31:0] Result, Dataout;
  wire [2:0] Mode_Type;

//   instruction_fetch IF(
//     .clk(clk), 
//     .rst(rst), 
//     .pc(pc), 
//     .instruction(instruction)
//   );
    Instruction_Fetch I1(
    .clk(clk), 
    .reset(reset), 
    .PC(PC), 
    .Instruction(Instruction)
  );


  Decode I2(
    .Instruction(Instruction), 
    .Opcode_ALU(Opcode_ALU), 
    .Opcode_Branch(Opcode_Branch), 
    .Opcode_Data(Opcode_Data),
    .Mode(Mode_Type)
  );
// always@(*)begin
//   $display("%d ---- %d ---- %d ----",Opcode_ALU, Opcode_Branch, Opcode_Data);
// end
// wire [31:0] Data1, Data2;
// assign Data1= Register[Instruction[25:21]];
// assign Data2= Register[Instruction[20:16]];



  ALU I3(
    .Data1(Register[Instruction[25:21]]), 
    .Data2(Register[Instruction[20:16]]), 
    .Immediate_Branch(Instruction[15:0]),
    .Opcode_ALU(Opcode_ALU), 
    .Result(Result)
  );

  Branching I4(
    .Data1(Register[Instruction[25:21]]),
    .Data2(Register[Instruction[20:16]]),
    .Immediate_Jump(Instruction[25:0]), 
    .PC(PC), 
    .Opcode_Branch(Opcode_Branch), 
    .Next_PC(Next_PC), 
    .ra(ra)
  );
//   wire [15:0] Offset;
//   assign Offset= Instruction[15:0];

  Store_Load I5( 
    .reset(reset), 
    .PC(PC),
    .Data_Value(Register[Instruction[20:16]]), 
    .Address(Register[Instruction[25:21]]),
    .Offset(Instruction[15:0]),
    .Opcode_Data(Opcode_Data),
    .Dataout(Dataout)
  );

  initial begin
    Register[0]=32'd0;
    PC=9'd0;
  end

  always @(negedge clk) begin
    case(Mode_Type)
      3'b000: begin
        PC = Next_PC + 1;
      end
      3'b001: begin
        PC = PC + 1;
        Register[Instruction[15:11]] = Result;
      end
      3'b010: begin
        PC = PC + 1;
        Register[Instruction[20:16]] = Result;
      end
      3'b011: begin
        PC = PC + 1;
      end
      3'b100: begin
        PC = PC + 1;
        Register[Instruction[20:16]] = Dataout;
      end
    endcase
    $display("Register[%d]: %d Register[%d]: %d Register[%d]: %d Instruction %d PC: %d", Instruction[25:21], Register[Instruction[25:21]], Instruction[20:16], Register[Instruction[20:16]], Instruction[15:11], Register[Instruction[15:11]], Instruction,PC);
  end
endmodule

Assignment_7_Final/Main_Controller_test_bench.v
`include "Main_Controller.v"
`timescale 1ps/1ps

module Main_Controller_test_bench;
    reg clk, reset;   
    Main_Controller M1(.clk(clk), .reset(reset));  ///calling main controller function for computation 

    initial begin                   //setting clock and reset values to zero
        clk=0;
        reset=0;
    end

    always #10 clk = ~clk;     // will invert clk value 
    initial begin
        $dumpfile("Main_Controller_test_bench.vcd");    
        $dumpvars(0, Main_Controller_test_bench);
        #15000 $finish;    //finish the whole program after 10000
    end


endmodule

Assignment_7_Final/Main_Controller_test_bench.vcd
$date
	Wed Apr 12 22:39:00 2023
$end
$version
	Icarus Verilog
$end
$timescale
	1ps
$end
$scope module Main_Controller_test_bench $end
$var reg 1 ! clk $end
$var reg 1 " reset $end
$scope module M1 $end
$var wire 1 ! clk $end
$var wire 1 " reset $end
$var wire 10 # ra [9:0] $end
$var wire 32 $ Result [31:0] $end
$var wire 1 % Opcode_Data $end
$var wire 4 & Opcode_Branch [3:0] $end
$var wire 4 ' Opcode_ALU [3:0] $end
$var wire 10 ( Next_PC [9:0] $end
$var wire 3 ) Mode_Type [2:0] $end
$var wire 32 * Instruction [31:0] $end
$var wire 32 + Dataout [31:0] $end
$var reg 10 , PC [9:0] $end
$scope module I1 $end
$var wire 10 - PC [9:0] $end
$var wire 1 ! clk $end
$var wire 1 " reset $end
$var wire 32 . Instruction [31:0] $end
$scope module IM $end
$var wire 10 / Instruction_Address [9:0] $end
$var wire 1 ! clk $end
$var wire 1 " reset $end
$var reg 32 0 Instruction [31:0] $end
$var integer 32 1 i [31:0] $end
$upscope $end
$upscope $end
$scope module I2 $end
$var wire 32 2 Instruction [31:0] $end
$var wire 6 3 opcode [5:0] $end
$var wire 6 4 func [5:0] $end
$var reg 3 5 Mode [2:0] $end
$var reg 4 6 Opcode_ALU [3:0] $end
$var reg 4 7 Opcode_Branch [3:0] $end
$var reg 1 % Opcode_Data $end
$upscope $end
$scope module I3 $end
$var wire 32 8 Data1 [31:0] $end
$var wire 32 9 Data2 [31:0] $end
$var wire 16 : Immediate_Branch [15:0] $end
$var wire 4 ; Opcode_ALU [3:0] $end
$var reg 32 < Result [31:0] $end
$upscope $end
$scope module I4 $end
$var wire 32 = Data1 [31:0] $end
$var wire 32 > Data2 [31:0] $end
$var wire 26 ? Immediate_Jump [25:0] $end
$var wire 4 @ Opcode_Branch [3:0] $end
$var wire 10 A PC [9:0] $end
$var reg 10 B Next_PC [9:0] $end
$var reg 10 C ra [9:0] $end
$upscope $end
$scope module I5 $end
$var wire 32 D Address [31:0] $end
$var wire 32 E Data_Value [31:0] $end
$var wire 16 F Offset [15:0] $end
$var wire 1 % Opcode_Data $end
$var wire 10 G PC [9:0] $end
$var wire 1 " reset $end
$var reg 32 H Dataout [31:0] $end
$var integer 32 I i [31:0] $end
$upscope $end
$upscope $end
$upscope $end
$enddefinitions $end
$comment Show the parameter values. $end
$dumpall
$end
#0
$dumpvars
b10000000000 I
bx H
b0 G
bx F
bx E
bx D
bx C
bx B
b0 A
bx @
bx ?
bx >
bx =
bx <
bx ;
bx :
bx 9
bx 8
bx 7
bx 6
bx 5
bx 4
bx 3
bx 2
b11110 1
bx 0
b0 /
bx .
b0 -
b0 ,
bx +
bx *
bx )
bx (
bx '
bx &
x%
bx $
bx #
0"
0!
$end
#10
b1010 +
b1010 H
0%
b100 )
b100 5
b100011 3
b0 4
b0 F
b0 D
b10000000000000000000 ?
b0 =
b0 :
b0 8
b10001100000010000000000000000000 *
b10001100000010000000000000000000 .
b10001100000010000000000000000000 0
b10001100000010000000000000000000 2
1!
#20
b1010 9
b1010 >
b1010 E
b1 ,
b1 -
b1 /
b1 A
b1 G
0!
#30
bx E
b10010000000000000000 ?
bx >
bx 9
b10001100000010010000000000000000 *
b10001100000010010000000000000000 .
b10001100000010010000000000000000 0
b10001100000010010000000000000000 2
1!
#40
b1010 9
b1010 >
b1010 E
b10 ,
b10 -
b10 /
b10 A
b10 G
0!
#50
b1 $
b1 <
b100 '
b100 6
b100 ;
b10 )
b10 5
b101 +
b101 H
b1000 3
b1 4
b1 F
bx E
b1010000000000000001 ?
bx >
b1 :
bx 9
b100000000001010000000000000001 *
b100000000001010000000000000001 .
b100000000001010000000000000001 0
b100000000001010000000000000001 2
1!
#60
b1 9
b1 >
b1 E
b11 ,
b11 -
b11 /
b11 A
b11 G
0!
#70
b10 )
b10 5
b1100 +
b1100 H
b1001 $
b1001 <
b111111 4
b1111111111111111 F
b1010 D
b1010 E
b1001010011111111111111111 ?
b1010 >
b1010 =
b1111111111111111 :
b1010 9
b1010 8
b100001001010011111111111111111 *
b100001001010011111111111111111 .
b100001001010011111111111111111 0
b100001001010011111111111111111 2
1!
#80
b1000 $
b1000 <
b0 +
b0 H
b1001 8
b1001 9
b1001 =
b1001 >
b1001 E
b1001 D
b100 ,
b100 -
b100 /
b100 A
b100 G
0!
#90
b100 (
b100 B
b100 &
b100 7
b100 @
b0 )
b0 5
b11100 $
b11100 <
b11001 3
b10011 4
b10011 F
b0 E
b1001000000000000000010011 ?
b0 >
b10011 :
b0 9
b1100101001000000000000000010011 *
b1100101001000000000000000010011 .
b1100101001000000000000000010011 0
b1100101001000000000000000010011 2
1!
#100
b101 (
b101 B
b101 ,
b101 -
b101 /
b101 A
b101 G
0!
#110
b0 '
b0 6
b0 ;
b1 )
b1 5
b0 $
b0 <
b0 3
b100000 4
b101000000100000 F
b0 D
b101000000100000 ?
b0 =
b101000000100000 :
b0 8
b101000000100000 *
b101000000100000 .
b101000000100000 0
b101000000100000 2
1!
#120
b110 (
b110 B
b110 ,
b110 -
b110 /
b110 A
b110 G
0!
#130
b11 &
b11 7
b11 @
b0 )
b0 5
b110 (
b110 B
b1001 $
b1001 <
b11000 3
b111100 4
b1111111111111100 F
b1001 E
b1010010011111111111111100 ?
b1001 >
b1111111111111100 :
b1001 9
b1100001010010011111111111111100 *
b1100001010010011111111111111100 .
b1100001010010011111111111111100 0
b1100001010010011111111111111100 2
1!
#140
b111 (
b111 B
b111 ,
b111 -
b111 /
b111 A
b111 G
0!
#150
b1 )
b1 5
b100111 (
b100111 B
b1 $
b1 <
b0 3
b100000 4
b111000000100000 F
b1 D
b0 E
b101010100111000000100000 ?
b0 >
b1 =
b111000000100000 :
b0 9
b1 8
b101010100111000000100000 *
b101010100111000000100000 .
b101010100111000000100000 0
b101010100111000000100000 2
1!
#160
b101000 (
b101000 B
b1000 ,
b1000 -
b1000 /
b1000 A
b1000 G
0!
#170
b100 )
b100 5
b101 +
b101 H
b1000 (
b1000 B
bx $
bx <
b100011 3
b0 4
b0 F
bx E
b1110010110000000000000000 ?
bx >
b0 :
bx 9
b10001101110010110000000000000000 *
b10001101110010110000000000000000 .
b10001101110010110000000000000000 0
b10001101110010110000000000000000 2
1!
#180
b110 $
b110 <
b1001 (
b1001 B
b101 9
b101 >
b101 E
b1001 ,
b1001 -
b1001 /
b1001 A
b1001 G
0!
#190
b100 '
b100 6
b100 ;
b10 )
b10 5
b10xx (
b10xx B
b1 $
b1 <
b1000 3
b1 4
b1 F
b0 D
bx E
b1010011000000000000000001 ?
bx >
b0 =
b1 :
bx 9
b0 8
b100001010011000000000000000001 *
b100001010011000000000000000001 .
b100001010011000000000000000001 0
b100001010011000000000000000001 2
1!
#200
b1010 (
b1010 B
b1 9
b1 >
b1 E
b1010 ,
b1010 -
b1010 /
b1010 A
b1010 G
0!
#210
b0 '
b0 6
b0 ;
b1 )
b1 5
b0 +
b0 H
b101010 (
b101010 B
b10 $
b10 <
b0 3
b100000 4
b111000000100000 F
b1 D
b101011000111000000100000 ?
b1 =
b111000000100000 :
b1 8
b101011000111000000100000 *
b101011000111000000100000 .
b101011000111000000100000 0
b101011000111000000100000 2
1!
#220
b101011 (
b101011 B
b1011 ,
b1011 -
b1011 /
b1011 A
b1011 G
0!
#230
b100 )
b100 5
b10 +
b10 H
b1011 (
b1011 B
bx $
bx <
b100011 3
b0 4
b0 F
b10 D
bx E
b1110011010000000000000000 ?
bx >
b10 =
b0 :
bx 9
b10 8
b10001101110011010000000000000000 *
b10001101110011010000000000000000 .
b10001101110011010000000000000000 0
b10001101110011010000000000000000 2
1!
#240
b100 $
b100 <
b1100 (
b1100 B
b10 9
b10 >
b10 E
b1100 ,
b1100 -
b1100 /
b1100 A
b1100 G
0!
#250
b1110 (
b1110 B
b100 &
b100 7
b100 @
b0 )
b0 5
b1011 +
b1011 H
b111 $
b111 <
b11001 3
b10 4
b10 F
b101 E
b1101010110000000000000010 ?
b101 >
b10 :
b101 9
b1100101101010110000000000000010 *
b1100101101010110000000000000010 .
b1100101101010110000000000000010 0
b1100101101010110000000000000010 2
1!
#260
b10001 (
b10001 B
b1111 ,
b1111 -
b1111 /
b1111 A
b1111 G
0!
#270
b1 )
b1 5
b0 +
b0 H
b1111 (
b1111 B
b10 $
b10 <
b0 3
b100000 4
b111000000100000 F
b1 D
b1 E
b101011000111000000100000 ?
b1 >
b1 =
b111000000100000 :
b1 9
b1 8
b101011000111000000100000 *
b101011000111000000100000 .
b101011000111000000100000 0
b101011000111000000100000 2
1!
#280
b10000 (
b10000 B
b10000 ,
b10000 -
b10000 /
b10000 A
b10000 G
0!
#290
1%
b11 )
b11 5
b10 +
b10 H
b111 $
b111 <
b101011 3
b0 4
b0 F
b10 D
b101 E
b1110010110000000000000000 ?
b101 >
b10 =
b0 :
b101 9
b10 8
b10101101110010110000000000000000 *
b10101101110010110000000000000000 .
b10101101110010110000000000000000 0
b10101101110010110000000000000000 2
1!
#300
b10001 (
b10001 B
b10001 ,
b10001 -
b10001 /
b10001 A
b10001 G
0!
#310
b0 +
b0 H
0%
b1 )
b1 5
b1 $
b1 <
b0 3
b100000 4
b111000000100000 F
b1 D
b0 E
b101010100111000000100000 ?
b0 >
b1 =
b111000000100000 :
b0 9
b1 8
b101010100111000000100000 *
b101010100111000000100000 .
b101010100111000000100000 0
b101010100111000000100000 2
1!
#320
b10010 (
b10010 B
b10010 ,
b10010 -
b10010 /
b10010 A
b10010 G
0!
#330
1%
b11 )
b11 5
b101 +
b101 H
b11 $
b11 <
b101011 3
b0 4
b0 F
b10 E
b1110011010000000000000000 ?
b10 >
b0 :
b10 9
b10101101110011010000000000000000 *
b10101101110011010000000000000000 .
b10101101110011010000000000000000 0
b10101101110011010000000000000000 2
1!
#340
b10011 (
b10011 B
b10011 ,
b10011 -
b10011 /
b10011 A
b10011 G
0!
#350
b1100 (
b1100 B
b0 +
b0 H
b110 &
b110 7
b110 @
0%
b0 )
b0 5
b0 $
b0 <
b10 3
b1101 4
b1101 F
b0 D
b0 E
b1101 ?
b0 >
b0 =
b1101 :
b0 9
b0 8
b1000000000000000000000001101 *
b1000000000000000000000001101 .
b1000000000000000000000001101 0
b1000000000000000000000001101 2
1!
#360
b1101 ,
b1101 -
b1101 /
b1101 A
b1101 G
0!
#370
b1 $
b1 <
b10 )
b10 5
b100 '
b100 6
b100 ;
b10 +
b10 H
b0 (
b0 B
b1000 3
b1 4
b1 F
b1010010100000000000000001 ?
b1 :
b100001010010100000000000000001 *
b100001010010100000000000000001 .
b100001010010100000000000000001 0
b100001010010100000000000000001 2
1!
#380
b10 $
b10 <
b101 +
b101 H
b1 8
b1 9
b1 =
b1 >
b1 E
b1 D
b1110 ,
b1110 -
b1110 /
b1110 A
b1110 G
0!
#390
b0 )
b0 5
b100 +
b100 H
b101 (
b101 B
b110 $
b110 <
b10 3
b110 4
b110 F
b0 D
b0 E
b110 ?
b0 >
b0 =
b110 :
b0 9
b0 8
b1000000000000000000000000110 *
b1000000000000000000000000110 .
b1000000000000000000000000110 0
b1000000000000000000000000110 2
1!
#400
b110 ,
b110 -
b110 /
b110 A
b110 G
0!
#410
b11 &
b11 7
b11 @
b0 +
b0 H
b110 (
b110 B
b11111111111111111111111111111101 $
b11111111111111111111111111111101 <
b11000 3
b111100 4
b1111111111111100 F
b1 D
b1001 E
b1010010011111111111111100 ?
b1001 >
b1 =
b1111111111111100 :
b1001 9
b1 8
b1100001010010011111111111111100 *
b1100001010010011111111111111100 .
b1100001010010011111111111111100 0
b1100001010010011111111111111100 2
1!
#420
b111 (
b111 B
b111 ,
b111 -
b111 /
b111 A
b111 G
0!
#430
b0 '
b0 6
b0 ;
b1 )
b1 5
b100111 (
b100111 B
b10 $
b10 <
b0 3
b100000 4
b111000000100000 F
b1 E
b101010100111000000100000 ?
b1 >
b111000000100000 :
b1 9
b101010100111000000100000 *
b101010100111000000100000 .
b101010100111000000100000 0
b101010100111000000100000 2
1!
#440
b101000 (
b101000 B
b1000 ,
b1000 -
b1000 /
b1000 A
b1000 G
0!
#450
b100 )
b100 5
b101 +
b101 H
b1000 (
b1000 B
b111 $
b111 <
b100011 3
b0 4
b0 F
b10 D
b101 E
b1110010110000000000000000 ?
b101 >
b10 =
b0 :
b101 9
b10 8
b10001101110010110000000000000000 *
b10001101110010110000000000000000 .
b10001101110010110000000000000000 0
b10001101110010110000000000000000 2
1!
#460
b1001 (
b1001 B
b1001 ,
b1001 -
b1001 /
b1001 A
b1001 G
0!
#470
b100 '
b100 6
b100 ;
b10 )
b10 5
b1010 (
b1010 B
b10 $
b10 <
b1000 3
b1 4
b1 F
b1 D
b1 E
b1010011000000000000000001 ?
b1 >
b1 =
b1 :
b1 9
b1 8
b100001010011000000000000000001 *
b100001010011000000000000000001 .
b100001010011000000000000000001 0
b100001010011000000000000000001 2
1!
#480
b10 9
b10 >
b10 E
b1010 ,
b1010 -
b1010 /
b1010 A
b1010 G
0!
